haplo/__about__.py
haplo/__init__.py
haplo/analysis.py
haplo/data_paths.py
haplo/data_preparation.py
haplo/distributed.py
haplo/export_onnx.py
haplo/logging.py
haplo/losses.py
haplo/models.py
haplo/nicer_dataset.py
haplo/nicer_parameters_to_phase_amplitudes_infer.py
haplo/nicer_transform.py
haplo/pbs_helper.py
haplo/rank_constant_distributed_sampler.py
haplo/train_hyperparameter_configuration.py
haplo/train_logging_configuration.py
haplo/train_session.py
haplo/train_system_configuration.py
haplo/unwrap_model.py
haplo/wandb_liaison.py
haplo/internal/__init__.py
haplo/internal/combine_split_mcmc_output_files.py
haplo/internal/constantinos_kalapotharakos_format.py
haplo/internal/data_conversion.py
haplo/internal/mcmc_output_analysis.py
haplo/internal/mcmc_output_file_manipulations.py
haplo/internal/xarray_zarr_dataset.py
haplo-0.19.0.dist-info/METADATA
haplo-0.19.0.dist-info/WHEEL
haplo-0.19.0.dist-info/RECORD
