Metadata-Version: 2.3
Name: haplo
Version: 0.19.0
Author-email: Greg Olmschenk <greg@olmschenk.com>
Requires-Python: >=3.11
Requires-Dist: bokeh>=3.2.2
Requires-Dist: connectorx>=0.3.2
Requires-Dist: dask>=2023.1.1
Requires-Dist: filelock>=3.12.3
Requires-Dist: furo>=2023.9.10
Requires-Dist: myst-parser
Requires-Dist: numcodecs!=0.16.0,>=0.15.0
Requires-Dist: numpy>=1.25.2
Requires-Dist: onnx>=1.14.1
Requires-Dist: onnxruntime>=1.15.1
Requires-Dist: pandas>=2.1.0
Requires-Dist: polars>=0.20
Requires-Dist: pyarrow>=13.0.0
Requires-Dist: pytest>=7.4.2
Requires-Dist: sqlalchemy>=2.0.21
Requires-Dist: stringcase>=1.2.0
Requires-Dist: tenacity>=8.2.3
Requires-Dist: torch!=2.4.0,!=2.4.1; platform_system == 'Windows'
Requires-Dist: torch>=2.0.1
Requires-Dist: wandb>=0.18.0
Requires-Dist: xarray>2023.1.0
Requires-Dist: zarr<3.0.0,>=2.0.0
